{
  "last_updated": "2026-03-12T17:59:46.333339Z",
  "source_url": "https://data.bzerox.org/graph/",
  "stats": {
    "downloaded": 0,
    "updated": 8,
    "errors": 0,
    "skipped": 1
  },
  "files": [
    {
      "path": "githubERC20RewardsTestnet.json",
      "size": 182,
      "modified": "2026-03-12T17:59:34.338334Z",
      "md5": "f4559b4fa75caf8238c951742f6506a2"
    },
    {
      "path": "B0x_Staking_Rich_List_logs_testnet.json",
      "size": 819,
      "modified": "2026-03-12T17:59:45.882268Z",
      "md5": "849c0f10f130f9a7bafbd2decf281f5a"
    },
    {
      "path": "mined_blocks_testnet.js",
      "size": 354,
      "modified": "2026-03-12T17:59:34.338334Z",
      "md5": "04f660f0973f48b1fa99b58e20d0b82d"
    },
    {
      "path": "RichList__MainnetETH_holders.json",
      "size": 1074,
      "modified": "2026-03-12T17:59:46.028549Z",
      "md5": "3c879d5f6c2fec7505f27bf97f482f26"
    },
    {
      "path": "price_data_bwork.json",
      "size": 7080,
      "modified": "2026-03-12T17:59:46.097848Z",
      "md5": "1b747c9b9b8eecc3808495b5d9250283"
    },
    {
      "path": "RichList_RightsTo0xBTC_MainnetETH_holders.json",
      "size": 770,
      "modified": "2026-03-12T17:59:45.996891Z",
      "md5": "d2fec8d742f4cef60431e2682ff0a62d"
    },
    {
      "path": "uu_mined_blocks_testnet.json",
      "size": 691202,
      "modified": "2026-03-12T17:59:46.332669Z",
      "md5": "e7e5e97dfe2890d651b7b16bad412d2a"
    },
    {
      "path": "testnet_uniswap_v4_data.json",
      "size": 14349,
      "modified": "2026-03-12T17:59:46.139990Z",
      "md5": "efa95ce6c3a05fda7f52bcf62428863d"
    },
    {
      "path": "mined_blocks_testnet.json",
      "size": 278126,
      "modified": "2026-03-12T17:59:34.339646Z",
      "md5": "ec38b30e891cf22ec21ad931cfd3bb82"
    },
    {
      "path": "RichList_B0x_testnet.json",
      "size": 2238,
      "modified": "2026-03-12T17:59:45.920020Z",
      "md5": "e2ecfa5685441d525a44af6a87f98f98"
    },
    {
      "path": "RichList_B0x_testnet_miners.json",
      "size": 1106,
      "modified": "2026-03-12T17:59:45.959008Z",
      "md5": "8a6664b8b2e2e4d27794e4a4568e00c8"
    }
  ]
}