{
  "last_updated": "2026-01-30T17:05:57.364206Z",
  "source_url": "https://data.bzerox.org/graph/",
  "stats": {
    "downloaded": 0,
    "updated": 8,
    "errors": 0,
    "skipped": 1
  },
  "files": [
    {
      "path": "RichList_RightsTo0xBTC_MainnetETH_holders.json",
      "size": 770,
      "modified": "2026-01-30T17:05:56.735856Z",
      "md5": "849ccfc1e15060ab2ab54204ceaa3adf"
    },
    {
      "path": "mined_blocks_testnet.json",
      "size": 278126,
      "modified": "2026-01-30T17:05:46.337672Z",
      "md5": "ec38b30e891cf22ec21ad931cfd3bb82"
    },
    {
      "path": "testnet_uniswap_v4_data.json",
      "size": 14349,
      "modified": "2026-01-30T17:05:57.013853Z",
      "md5": "f8d1f63a08d8961cbf65495c3e8c0a79"
    },
    {
      "path": "price_data_bwork.json",
      "size": 6990,
      "modified": "2026-01-30T17:05:56.941854Z",
      "md5": "7620af7a513dfc37546f31d92e613705"
    },
    {
      "path": "mined_blocks_testnet.js",
      "size": 354,
      "modified": "2026-01-30T17:05:46.336672Z",
      "md5": "04f660f0973f48b1fa99b58e20d0b82d"
    },
    {
      "path": "RichList_B0x_testnet.json",
      "size": 2238,
      "modified": "2026-01-30T17:05:56.604858Z",
      "md5": "7c0d9a3a98343bb3febc778eec886c4d"
    },
    {
      "path": "RichList_B0x_testnet_miners.json",
      "size": 1106,
      "modified": "2026-01-30T17:05:56.669857Z",
      "md5": "4ad0940a15897231db1f4e5357c41b02"
    },
    {
      "path": "B0x_Staking_Rich_List_logs_testnet.json",
      "size": 819,
      "modified": "2026-01-30T17:05:56.534858Z",
      "md5": "dfe9bbfd8dd96e7e6f74fe645f8208c9"
    },
    {
      "path": "RichList__MainnetETH_holders.json",
      "size": 1074,
      "modified": "2026-01-30T17:05:56.805856Z",
      "md5": "73d9993a8344ca37b89481f1e6369e8b"
    },
    {
      "path": "githubERC20RewardsTestnet.json",
      "size": 182,
      "modified": "2026-01-30T17:05:46.336672Z",
      "md5": "f4559b4fa75caf8238c951742f6506a2"
    },
    {
      "path": "uu_mined_blocks_testnet.json",
      "size": 691202,
      "modified": "2026-01-30T17:05:57.361853Z",
      "md5": "c1f67901dbc1a27210381d2da4a2c07d"
    }
  ]
}