{
  "last_updated": "2025-10-19T17:12:48.132811Z",
  "source_url": "https://data.bzerox.org/graph/",
  "stats": {
    "downloaded": 0,
    "updated": 8,
    "errors": 0,
    "skipped": 1
  },
  "files": [
    {
      "path": "uu_mined_blocks_testnet.json",
      "size": 474690,
      "modified": "2025-10-19T17:12:48.132362Z",
      "md5": "bed5d289a1db0691f1af2253af45172b"
    },
    {
      "path": "RichList_B0x_testnet_miners.json",
      "size": 778,
      "modified": "2025-10-19T17:12:47.695522Z",
      "md5": "9a6dedc102d977ca2993889497e99d51"
    },
    {
      "path": "mined_blocks_testnet.json",
      "size": 278126,
      "modified": "2025-10-19T17:12:40.903705Z",
      "md5": "ec38b30e891cf22ec21ad931cfd3bb82"
    },
    {
      "path": "githubERC20RewardsTestnet.json",
      "size": 182,
      "modified": "2025-10-19T17:12:40.902958Z",
      "md5": "f4559b4fa75caf8238c951742f6506a2"
    },
    {
      "path": "RichList_B0x_testnet.json",
      "size": 1771,
      "modified": "2025-10-19T17:12:47.651113Z",
      "md5": "7c357eac0d49c94597c00a212d53b6f5"
    },
    {
      "path": "RichList__MainnetETH_holders.json",
      "size": 1076,
      "modified": "2025-10-19T17:12:47.785401Z",
      "md5": "6445be30a6c4cd224940b430dcbf2a37"
    },
    {
      "path": "B0x_Staking_Rich_List_logs_testnet.json",
      "size": 819,
      "modified": "2025-10-19T17:12:47.605359Z",
      "md5": "2e36b94d928e81c2a5e44549057b2fc0"
    },
    {
      "path": "RichList_RightsTo0xBTC_MainnetETH_holders.json",
      "size": 770,
      "modified": "2025-10-19T17:12:47.738848Z",
      "md5": "80cd3700ac8f99ae5ed6443633df0814"
    },
    {
      "path": "mined_blocks_testnet.js",
      "size": 354,
      "modified": "2025-10-19T17:12:40.902958Z",
      "md5": "04f660f0973f48b1fa99b58e20d0b82d"
    },
    {
      "path": "price_data_bwork.json",
      "size": 6925,
      "modified": "2025-10-19T17:12:47.873121Z",
      "md5": "afdab3b59b27cf9198fae7018e2a16d0"
    },
    {
      "path": "testnet_uniswap_v4_data.json",
      "size": 14349,
      "modified": "2025-10-19T17:12:47.922747Z",
      "md5": "78157ff19200c386a67dbf63a67515ee"
    }
  ]
}