{
  "last_updated": "2025-10-21T07:52:43.928272Z",
  "source_url": "https://data.bzerox.org/graph/",
  "stats": {
    "downloaded": 0,
    "updated": 8,
    "errors": 0,
    "skipped": 1
  },
  "files": [
    {
      "path": "RichList_RightsTo0xBTC_MainnetETH_holders.json",
      "size": 770,
      "modified": "2025-10-21T07:52:43.530278Z",
      "md5": "e17af3a5b6995a21f03134c9812e7be5"
    },
    {
      "path": "mined_blocks_testnet.json",
      "size": 278126,
      "modified": "2025-10-21T07:52:35.308257Z",
      "md5": "ec38b30e891cf22ec21ad931cfd3bb82"
    },
    {
      "path": "testnet_uniswap_v4_data.json",
      "size": 14349,
      "modified": "2025-10-21T07:52:43.705279Z",
      "md5": "921312ebc94b3bc3f7de9e5aa995b7c6"
    },
    {
      "path": "price_data_bwork.json",
      "size": 6871,
      "modified": "2025-10-21T07:52:43.659279Z",
      "md5": "d00f8e0e0e6f7413a99a314347a03646"
    },
    {
      "path": "mined_blocks_testnet.js",
      "size": 354,
      "modified": "2025-10-21T07:52:35.307256Z",
      "md5": "04f660f0973f48b1fa99b58e20d0b82d"
    },
    {
      "path": "RichList_B0x_testnet.json",
      "size": 1771,
      "modified": "2025-10-21T07:52:43.447278Z",
      "md5": "04de4d0c5401938ee74369d7f1536167"
    },
    {
      "path": "RichList_B0x_testnet_miners.json",
      "size": 778,
      "modified": "2025-10-21T07:52:43.490278Z",
      "md5": "18db100c627fa50667fa16f00a397a76"
    },
    {
      "path": "B0x_Staking_Rich_List_logs_testnet.json",
      "size": 819,
      "modified": "2025-10-21T07:52:43.405277Z",
      "md5": "6aca2312e4a2f8e3ee27e5634b7d17dc"
    },
    {
      "path": "RichList__MainnetETH_holders.json",
      "size": 1076,
      "modified": "2025-10-21T07:52:43.572278Z",
      "md5": "6289234fe7e283dc40a08e56bd473fd7"
    },
    {
      "path": "githubERC20RewardsTestnet.json",
      "size": 182,
      "modified": "2025-10-21T07:52:35.307256Z",
      "md5": "f4559b4fa75caf8238c951742f6506a2"
    },
    {
      "path": "uu_mined_blocks_testnet.json",
      "size": 474690,
      "modified": "2025-10-21T07:52:43.927278Z",
      "md5": "872ae7ae281c7ed8a5c8271def5b935c"
    }
  ]
}