{
  "last_updated": "2025-10-12T04:51:56.822114Z",
  "source_url": "https://data.bzerox.org/graph/",
  "stats": {
    "downloaded": 0,
    "updated": 7,
    "errors": 0,
    "skipped": 2
  },
  "files": [
    {
      "path": "RichList_RightsTo0xBTC_MainnetETH_holders.json",
      "size": 770,
      "modified": "2025-10-12T04:51:56.429059Z",
      "md5": "6e6a05a03bbe50e5a3d00e1284b27e9a"
    },
    {
      "path": "mined_blocks_testnet.json",
      "size": 278126,
      "modified": "2025-10-12T04:51:49.721006Z",
      "md5": "ec38b30e891cf22ec21ad931cfd3bb82"
    },
    {
      "path": "testnet_uniswap_v4_data.json",
      "size": 14349,
      "modified": "2025-10-12T04:51:56.585060Z",
      "md5": "8b9dbac08fb9bf3ce4da493ef8a83cd4"
    },
    {
      "path": "price_data_bwork.json",
      "size": 6806,
      "modified": "2025-10-12T04:51:56.544060Z",
      "md5": "140a46f682a5f714585da56eac106dab"
    },
    {
      "path": "mined_blocks_testnet.js",
      "size": 354,
      "modified": "2025-10-12T04:51:49.720006Z",
      "md5": "04f660f0973f48b1fa99b58e20d0b82d"
    },
    {
      "path": "RichList_B0x_testnet.json",
      "size": 1771,
      "modified": "2025-10-12T04:51:56.361058Z",
      "md5": "e0d7a855a0effb4410631feb9b3f1090"
    },
    {
      "path": "RichList_B0x_testnet_miners.json",
      "size": 778,
      "modified": "2025-10-12T04:51:56.396059Z",
      "md5": "0387dee572c3709a4549fcbf17a61937"
    },
    {
      "path": "B0x_Staking_Rich_List_logs_testnet.json",
      "size": 819,
      "modified": "2025-10-12T04:51:49.720006Z",
      "md5": "e0842f1e653fcfdb627ab2fe36492c7d"
    },
    {
      "path": "RichList__MainnetETH_holders.json",
      "size": 1076,
      "modified": "2025-10-12T04:51:56.463059Z",
      "md5": "88cd1e91dba47154d52fd3490f467ce3"
    },
    {
      "path": "githubERC20RewardsTestnet.json",
      "size": 182,
      "modified": "2025-10-12T04:51:49.720006Z",
      "md5": "f4559b4fa75caf8238c951742f6506a2"
    },
    {
      "path": "uu_mined_blocks_testnet.json",
      "size": 474690,
      "modified": "2025-10-12T04:51:56.820062Z",
      "md5": "34eeefc21f2959c56cdf6efd9deff1b7"
    }
  ]
}