{
  "last_updated": "2026-07-10T22:38:33.584945Z",
  "source_url": "https://data.bzerox.org/graph/",
  "stats": {
    "downloaded": 0,
    "updated": 8,
    "errors": 0,
    "skipped": 1
  },
  "files": [
    {
      "path": "RichList__MainnetETH_holders.json",
      "size": 1545138,
      "modified": "2026-07-10T22:38:33.259220Z",
      "md5": "c7bd1886fb7633ffae5045b6f9e33fb3"
    },
    {
      "path": "mined_blocks_testnet.js",
      "size": 354,
      "modified": "2026-07-10T22:38:20.228284Z",
      "md5": "04f660f0973f48b1fa99b58e20d0b82d"
    },
    {
      "path": "B0x_Staking_Rich_List_logs_testnet.json",
      "size": 819,
      "modified": "2026-07-10T22:38:32.226312Z",
      "md5": "31f703abf41d2007fca6a3a5cba115ba"
    },
    {
      "path": "RichList_B0x_testnet.json",
      "size": 2238,
      "modified": "2026-07-10T22:38:32.293116Z",
      "md5": "79106c8a0003049b4be3c891db48b450"
    },
    {
      "path": "mined_blocks_testnet.json",
      "size": 278126,
      "modified": "2026-07-10T22:38:20.229284Z",
      "md5": "ec38b30e891cf22ec21ad931cfd3bb82"
    },
    {
      "path": "price_data_bwork.json",
      "size": 7080,
      "modified": "2026-07-10T22:38:33.388811Z",
      "md5": "d52f02ac91580c473c687cccf890603d"
    },
    {
      "path": "RichList_B0x_testnet_miners.json",
      "size": 1106,
      "modified": "2026-07-10T22:38:32.359344Z",
      "md5": "bc4463d53f1927ccce0ab614d99d7f73"
    },
    {
      "path": "testnet_uniswap_v4_data.json",
      "size": 14349,
      "modified": "2026-07-10T22:38:33.458899Z",
      "md5": "14dda8eeef1c15c1416c37cb20a51190"
    },
    {
      "path": "githubERC20RewardsTestnet.json",
      "size": 182,
      "modified": "2026-07-10T22:38:20.228284Z",
      "md5": "f4559b4fa75caf8238c951742f6506a2"
    },
    {
      "path": "uu_mined_blocks_testnet.json",
      "size": 691202,
      "modified": "2026-07-10T22:38:33.584650Z",
      "md5": "726791556b0047551ba77ba77bf7da40"
    },
    {
      "path": "RichList_RightsTo0xBTC_MainnetETH_holders.json",
      "size": 1364625,
      "modified": "2026-07-10T22:38:33.048721Z",
      "md5": "ca44764ba1f749add720e2ee4fccd376"
    }
  ]
}