{
  "last_updated": "2026-03-04T07:51:31.101590Z",
  "source_url": "https://data.bzerox.org/graph/",
  "stats": {
    "downloaded": 0,
    "updated": 8,
    "errors": 0,
    "skipped": 1
  },
  "files": [
    {
      "path": "githubERC20RewardsTestnet.json",
      "size": 182,
      "modified": "2026-03-04T07:51:18.136869Z",
      "md5": "f4559b4fa75caf8238c951742f6506a2"
    },
    {
      "path": "B0x_Staking_Rich_List_logs_testnet.json",
      "size": 819,
      "modified": "2026-03-04T07:51:30.284598Z",
      "md5": "7385b4848f9f5d3c2be5d11d2076cb17"
    },
    {
      "path": "mined_blocks_testnet.js",
      "size": 354,
      "modified": "2026-03-04T07:51:18.136869Z",
      "md5": "04f660f0973f48b1fa99b58e20d0b82d"
    },
    {
      "path": "RichList__MainnetETH_holders.json",
      "size": 1074,
      "modified": "2026-03-04T07:51:30.542731Z",
      "md5": "7d7b0fd380317d2e5a812c1a6168d5c2"
    },
    {
      "path": "price_data_bwork.json",
      "size": 6966,
      "modified": "2026-03-04T07:51:30.671582Z",
      "md5": "4ce64e6203d05fc11a923a1d01da4c39"
    },
    {
      "path": "RichList_RightsTo0xBTC_MainnetETH_holders.json",
      "size": 770,
      "modified": "2026-03-04T07:51:30.479399Z",
      "md5": "7d62d099ee5967051e001ae08bbb94df"
    },
    {
      "path": "uu_mined_blocks_testnet.json",
      "size": 691202,
      "modified": "2026-03-04T07:51:31.100939Z",
      "md5": "9b667e4e3d949f86acf6d5ed5ebb25a8"
    },
    {
      "path": "testnet_uniswap_v4_data.json",
      "size": 14349,
      "modified": "2026-03-04T07:51:30.740082Z",
      "md5": "7d3d144bb962f5cacf7e283772263095"
    },
    {
      "path": "mined_blocks_testnet.json",
      "size": 278126,
      "modified": "2026-03-04T07:51:18.137779Z",
      "md5": "ec38b30e891cf22ec21ad931cfd3bb82"
    },
    {
      "path": "RichList_B0x_testnet.json",
      "size": 2238,
      "modified": "2026-03-04T07:51:30.353519Z",
      "md5": "64cacb61f57d634806812910682e1885"
    },
    {
      "path": "RichList_B0x_testnet_miners.json",
      "size": 1106,
      "modified": "2026-03-04T07:51:30.415524Z",
      "md5": "286efe1982b78428d3ba1dda018dc975"
    }
  ]
}