{
  "last_updated": "2026-03-22T17:27:31.074998Z",
  "source_url": "https://data.bzerox.org/graph/",
  "stats": {
    "downloaded": 0,
    "updated": 8,
    "errors": 0,
    "skipped": 1
  },
  "files": [
    {
      "path": "githubERC20RewardsTestnet.json",
      "size": 182,
      "modified": "2026-03-22T17:27:20.015163Z",
      "md5": "f4559b4fa75caf8238c951742f6506a2"
    },
    {
      "path": "B0x_Staking_Rich_List_logs_testnet.json",
      "size": 819,
      "modified": "2026-03-22T17:27:30.266819Z",
      "md5": "c24fc2a5782b3f2592dc9d741fe7d297"
    },
    {
      "path": "mined_blocks_testnet.js",
      "size": 354,
      "modified": "2026-03-22T17:27:20.015163Z",
      "md5": "04f660f0973f48b1fa99b58e20d0b82d"
    },
    {
      "path": "RichList__MainnetETH_holders.json",
      "size": 1074,
      "modified": "2026-03-22T17:27:30.500732Z",
      "md5": "1552b4ecbe99dc7a9c25d6a574cd0f24"
    },
    {
      "path": "price_data_bwork.json",
      "size": 7022,
      "modified": "2026-03-22T17:27:30.694106Z",
      "md5": "2064bbc2288adbf1b4a59efbbaeeee2e"
    },
    {
      "path": "RichList_RightsTo0xBTC_MainnetETH_holders.json",
      "size": 770,
      "modified": "2026-03-22T17:27:30.458863Z",
      "md5": "b51246f8b2b4eda6b1c829169a456594"
    },
    {
      "path": "uu_mined_blocks_testnet.json",
      "size": 691202,
      "modified": "2026-03-22T17:27:31.057745Z",
      "md5": "14c609190651031445f669fe76070d97"
    },
    {
      "path": "testnet_uniswap_v4_data.json",
      "size": 14349,
      "modified": "2026-03-22T17:27:30.810902Z",
      "md5": "1a4d4b5d65eb7c4729311ec85dff5207"
    },
    {
      "path": "mined_blocks_testnet.json",
      "size": 278126,
      "modified": "2026-03-22T17:27:20.015792Z",
      "md5": "ec38b30e891cf22ec21ad931cfd3bb82"
    },
    {
      "path": "RichList_B0x_testnet.json",
      "size": 2238,
      "modified": "2026-03-22T17:27:30.314333Z",
      "md5": "8f9eb92e69b61af7016dbad1b4ded5cb"
    },
    {
      "path": "RichList_B0x_testnet_miners.json",
      "size": 1106,
      "modified": "2026-03-22T17:27:30.363569Z",
      "md5": "2fe2aabff99f86388a04a267ca04669b"
    }
  ]
}