{
  "last_updated": "2026-03-22T23:37:13.962765Z",
  "source_url": "https://data.bzerox.org/graph/",
  "stats": {
    "downloaded": 0,
    "updated": 8,
    "errors": 0,
    "skipped": 1
  },
  "files": [
    {
      "path": "githubERC20RewardsTestnet.json",
      "size": 182,
      "modified": "2026-03-22T23:37:02.620370Z",
      "md5": "f4559b4fa75caf8238c951742f6506a2"
    },
    {
      "path": "B0x_Staking_Rich_List_logs_testnet.json",
      "size": 819,
      "modified": "2026-03-22T23:37:13.397217Z",
      "md5": "9ca423246dddcd5c90038c94b4462730"
    },
    {
      "path": "mined_blocks_testnet.js",
      "size": 354,
      "modified": "2026-03-22T23:37:02.620370Z",
      "md5": "04f660f0973f48b1fa99b58e20d0b82d"
    },
    {
      "path": "RichList__MainnetETH_holders.json",
      "size": 1074,
      "modified": "2026-03-22T23:37:13.538640Z",
      "md5": "6a38f15158588af8ebb7a41ff38b13cf"
    },
    {
      "path": "price_data_bwork.json",
      "size": 7081,
      "modified": "2026-03-22T23:37:13.611130Z",
      "md5": "8b09adf47db32e4ad68b97e8365f4d65"
    },
    {
      "path": "RichList_RightsTo0xBTC_MainnetETH_holders.json",
      "size": 770,
      "modified": "2026-03-22T23:37:13.502996Z",
      "md5": "b84f62799bca4990769cbbeaf20be3e2"
    },
    {
      "path": "uu_mined_blocks_testnet.json",
      "size": 691202,
      "modified": "2026-03-22T23:37:13.962144Z",
      "md5": "7635f66d43775ce3d4b424d8fe12347b"
    },
    {
      "path": "testnet_uniswap_v4_data.json",
      "size": 14349,
      "modified": "2026-03-22T23:37:13.653110Z",
      "md5": "6b44e21351e33b301461dd60198ccfd7"
    },
    {
      "path": "mined_blocks_testnet.json",
      "size": 278126,
      "modified": "2026-03-22T23:37:02.620566Z",
      "md5": "ec38b30e891cf22ec21ad931cfd3bb82"
    },
    {
      "path": "RichList_B0x_testnet.json",
      "size": 2238,
      "modified": "2026-03-22T23:37:13.436353Z",
      "md5": "3f07ca6b9d2f7b36c4185e34c0b6d731"
    },
    {
      "path": "RichList_B0x_testnet_miners.json",
      "size": 1106,
      "modified": "2026-03-22T23:37:13.468757Z",
      "md5": "c7b289165fc1fee1f9de373e470a15c3"
    }
  ]
}