{
  "last_updated": "2025-11-05T03:48:35.023292Z",
  "source_url": "https://data.bzerox.org/graph/",
  "stats": {
    "downloaded": 0,
    "updated": 6,
    "errors": 0,
    "skipped": 3
  },
  "files": [
    {
      "path": "RichList_RightsTo0xBTC_MainnetETH_holders.json",
      "size": 770,
      "modified": "2025-11-05T03:48:34.800551Z",
      "md5": "949cebcdf7e455541011f41ddab08bab"
    },
    {
      "path": "mined_blocks_testnet.json",
      "size": 278126,
      "modified": "2025-11-05T03:48:26.960525Z",
      "md5": "ec38b30e891cf22ec21ad931cfd3bb82"
    },
    {
      "path": "testnet_uniswap_v4_data.json",
      "size": 14349,
      "modified": "2025-11-05T03:48:34.893551Z",
      "md5": "c531206ef3de90af27d847fe4b4dcb25"
    },
    {
      "path": "price_data_bwork.json",
      "size": 6819,
      "modified": "2025-11-05T03:48:34.861551Z",
      "md5": "cbe3354a76b766a963dc5d914ce73c66"
    },
    {
      "path": "mined_blocks_testnet.js",
      "size": 354,
      "modified": "2025-11-05T03:48:26.959525Z",
      "md5": "04f660f0973f48b1fa99b58e20d0b82d"
    },
    {
      "path": "RichList_B0x_testnet.json",
      "size": 1774,
      "modified": "2025-11-05T03:48:26.959525Z",
      "md5": "fa8d673c18b245cfbb3bb8d7ee22c304"
    },
    {
      "path": "RichList_B0x_testnet_miners.json",
      "size": 780,
      "modified": "2025-11-05T03:48:26.959525Z",
      "md5": "7e4c23b12fc32d2b3624536115e28303"
    },
    {
      "path": "B0x_Staking_Rich_List_logs_testnet.json",
      "size": 819,
      "modified": "2025-11-05T03:48:34.725551Z",
      "md5": "4d7ad4e99294b8c4f7cf07a70ca53e99"
    },
    {
      "path": "RichList__MainnetETH_holders.json",
      "size": 1074,
      "modified": "2025-11-05T03:48:34.819551Z",
      "md5": "f48a3d9a15b33a382cfd5924c44c9578"
    },
    {
      "path": "githubERC20RewardsTestnet.json",
      "size": 182,
      "modified": "2025-11-05T03:48:26.959525Z",
      "md5": "f4559b4fa75caf8238c951742f6506a2"
    },
    {
      "path": "uu_mined_blocks_testnet.json",
      "size": 662033,
      "modified": "2025-11-05T03:48:35.021552Z",
      "md5": "48e1a202268a05af14f72d9804a67bbd"
    }
  ]
}