{
  "last_updated": "2026-01-23T08:48:11.647083Z",
  "source_url": "https://data.bzerox.org/graph/",
  "stats": {
    "downloaded": 0,
    "updated": 8,
    "errors": 0,
    "skipped": 1
  },
  "files": [
    {
      "path": "RichList_RightsTo0xBTC_MainnetETH_holders.json",
      "size": 770,
      "modified": "2026-01-23T08:48:11.221945Z",
      "md5": "e7ee7b17e152794c076fa0d5f64aae74"
    },
    {
      "path": "mined_blocks_testnet.json",
      "size": 278126,
      "modified": "2026-01-23T08:47:57.008708Z",
      "md5": "ec38b30e891cf22ec21ad931cfd3bb82"
    },
    {
      "path": "testnet_uniswap_v4_data.json",
      "size": 14349,
      "modified": "2026-01-23T08:48:11.401947Z",
      "md5": "4f73f00bc6f300ac608bce85217a137a"
    },
    {
      "path": "price_data_bwork.json",
      "size": 6931,
      "modified": "2026-01-23T08:48:11.347946Z",
      "md5": "9d92a0886205af5e3b9f4144ed79b8f6"
    },
    {
      "path": "mined_blocks_testnet.js",
      "size": 354,
      "modified": "2026-01-23T08:47:57.007709Z",
      "md5": "04f660f0973f48b1fa99b58e20d0b82d"
    },
    {
      "path": "RichList_B0x_testnet.json",
      "size": 2238,
      "modified": "2026-01-23T08:48:11.140944Z",
      "md5": "5b99414beb1b75328ed3b5d504aa6a84"
    },
    {
      "path": "RichList_B0x_testnet_miners.json",
      "size": 1106,
      "modified": "2026-01-23T08:48:11.179945Z",
      "md5": "fb4497a2da658c7acf20a129d897d73a"
    },
    {
      "path": "B0x_Staking_Rich_List_logs_testnet.json",
      "size": 819,
      "modified": "2026-01-23T08:48:11.094944Z",
      "md5": "7bf7543160f345bae2fd9f64248c8941"
    },
    {
      "path": "RichList__MainnetETH_holders.json",
      "size": 1074,
      "modified": "2026-01-23T08:48:11.262945Z",
      "md5": "4240ca99ea74964d66af5c626e5d9145"
    },
    {
      "path": "githubERC20RewardsTestnet.json",
      "size": 182,
      "modified": "2026-01-23T08:47:57.007709Z",
      "md5": "f4559b4fa75caf8238c951742f6506a2"
    },
    {
      "path": "uu_mined_blocks_testnet.json",
      "size": 691202,
      "modified": "2026-01-23T08:48:11.644948Z",
      "md5": "b5c2e75eb3620052dd29306131c38abf"
    }
  ]
}