{
  "last_updated": "2025-10-28T16:21:22.163369Z",
  "source_url": "https://data.bzerox.org/graph/",
  "stats": {
    "downloaded": 0,
    "updated": 8,
    "errors": 0,
    "skipped": 1
  },
  "files": [
    {
      "path": "RichList_RightsTo0xBTC_MainnetETH_holders.json",
      "size": 770,
      "modified": "2025-10-28T16:21:21.773604Z",
      "md5": "4aff3ee109fe80b32bb6132fa72fb573"
    },
    {
      "path": "mined_blocks_testnet.json",
      "size": 278126,
      "modified": "2025-10-28T16:21:14.164560Z",
      "md5": "ec38b30e891cf22ec21ad931cfd3bb82"
    },
    {
      "path": "testnet_uniswap_v4_data.json",
      "size": 14349,
      "modified": "2025-10-28T16:21:21.899605Z",
      "md5": "396a2e69b89d0dbe36380a8e8b564da4"
    },
    {
      "path": "price_data_bwork.json",
      "size": 6927,
      "modified": "2025-10-28T16:21:21.865605Z",
      "md5": "11d40730074a9ca6b0e193bf9b4d67af"
    },
    {
      "path": "mined_blocks_testnet.js",
      "size": 354,
      "modified": "2025-10-28T16:21:14.163560Z",
      "md5": "04f660f0973f48b1fa99b58e20d0b82d"
    },
    {
      "path": "RichList_B0x_testnet.json",
      "size": 1773,
      "modified": "2025-10-28T16:21:21.720604Z",
      "md5": "d266ff4b95cf3a75ead6847f7ffac358"
    },
    {
      "path": "RichList_B0x_testnet_miners.json",
      "size": 780,
      "modified": "2025-10-28T16:21:21.746604Z",
      "md5": "7d18a13853ad85c88fee78e56527b732"
    },
    {
      "path": "B0x_Staking_Rich_List_logs_testnet.json",
      "size": 819,
      "modified": "2025-10-28T16:21:21.689604Z",
      "md5": "d61ba6c8fdf5aa12a113dfbaebc559c2"
    },
    {
      "path": "RichList__MainnetETH_holders.json",
      "size": 1074,
      "modified": "2025-10-28T16:21:21.802604Z",
      "md5": "b73770254999645fdefe05c57fdc9718"
    },
    {
      "path": "githubERC20RewardsTestnet.json",
      "size": 182,
      "modified": "2025-10-28T16:21:14.163560Z",
      "md5": "f4559b4fa75caf8238c951742f6506a2"
    },
    {
      "path": "uu_mined_blocks_testnet.json",
      "size": 652709,
      "modified": "2025-10-28T16:21:22.162606Z",
      "md5": "1da490b6cca078e857ebc045397280fa"
    }
  ]
}