{
  "last_updated": "2026-03-17T14:08:03.490647Z",
  "source_url": "https://data.bzerox.org/graph/",
  "stats": {
    "downloaded": 0,
    "updated": 8,
    "errors": 0,
    "skipped": 1
  },
  "files": [
    {
      "path": "githubERC20RewardsTestnet.json",
      "size": 182,
      "modified": "2026-03-17T14:07:48.444350Z",
      "md5": "f4559b4fa75caf8238c951742f6506a2"
    },
    {
      "path": "B0x_Staking_Rich_List_logs_testnet.json",
      "size": 819,
      "modified": "2026-03-17T14:08:02.664356Z",
      "md5": "48a48411696ce8a54ffc7a48c8ba2719"
    },
    {
      "path": "mined_blocks_testnet.js",
      "size": 354,
      "modified": "2026-03-17T14:07:48.444350Z",
      "md5": "04f660f0973f48b1fa99b58e20d0b82d"
    },
    {
      "path": "RichList__MainnetETH_holders.json",
      "size": 1074,
      "modified": "2026-03-17T14:08:02.934285Z",
      "md5": "e3a44184d04e773673f0080dc894face"
    },
    {
      "path": "price_data_bwork.json",
      "size": 7024,
      "modified": "2026-03-17T14:08:03.070379Z",
      "md5": "b9f14204cb61125d8c6ecf3a0832a3a7"
    },
    {
      "path": "RichList_RightsTo0xBTC_MainnetETH_holders.json",
      "size": 770,
      "modified": "2026-03-17T14:08:02.868340Z",
      "md5": "af2c6d6ebccb52d65f11522e795aa76d"
    },
    {
      "path": "uu_mined_blocks_testnet.json",
      "size": 691202,
      "modified": "2026-03-17T14:08:03.489974Z",
      "md5": "89e32ee8530826d85db087a27b3d501e"
    },
    {
      "path": "testnet_uniswap_v4_data.json",
      "size": 14349,
      "modified": "2026-03-17T14:08:03.140824Z",
      "md5": "af1e561dce4ecc672cc0b0145586e5ac"
    },
    {
      "path": "mined_blocks_testnet.json",
      "size": 278126,
      "modified": "2026-03-17T14:07:48.444888Z",
      "md5": "ec38b30e891cf22ec21ad931cfd3bb82"
    },
    {
      "path": "RichList_B0x_testnet.json",
      "size": 2238,
      "modified": "2026-03-17T14:08:02.737328Z",
      "md5": "32b0f684c5e040097981fc103ef71743"
    },
    {
      "path": "RichList_B0x_testnet_miners.json",
      "size": 1106,
      "modified": "2026-03-17T14:08:02.802789Z",
      "md5": "8b2ae94ef79a68a1a456a6f3bf5f63ab"
    }
  ]
}