{
  "last_updated": "2025-10-27T20:25:54.409182Z",
  "source_url": "https://data.bzerox.org/graph/",
  "stats": {
    "downloaded": 0,
    "updated": 8,
    "errors": 0,
    "skipped": 1
  },
  "files": [
    {
      "path": "RichList_RightsTo0xBTC_MainnetETH_holders.json",
      "size": 770,
      "modified": "2025-10-27T20:25:53.762749Z",
      "md5": "bca57f8a928ab4bf41d7d217875c251b"
    },
    {
      "path": "mined_blocks_testnet.json",
      "size": 278126,
      "modified": "2025-10-27T20:25:42.982764Z",
      "md5": "ec38b30e891cf22ec21ad931cfd3bb82"
    },
    {
      "path": "testnet_uniswap_v4_data.json",
      "size": 14349,
      "modified": "2025-10-27T20:25:54.046749Z",
      "md5": "7e76a0fdcf814b2810d5241d4874f5eb"
    },
    {
      "path": "price_data_bwork.json",
      "size": 6985,
      "modified": "2025-10-27T20:25:53.972749Z",
      "md5": "25c98768a8aaaf129d0bf15e455fbc56"
    },
    {
      "path": "mined_blocks_testnet.js",
      "size": 354,
      "modified": "2025-10-27T20:25:42.981764Z",
      "md5": "04f660f0973f48b1fa99b58e20d0b82d"
    },
    {
      "path": "RichList_B0x_testnet.json",
      "size": 1775,
      "modified": "2025-10-27T20:25:53.625750Z",
      "md5": "a3045aca35446769b9cee714cb343acd"
    },
    {
      "path": "RichList_B0x_testnet_miners.json",
      "size": 781,
      "modified": "2025-10-27T20:25:53.694749Z",
      "md5": "6a9f0157fa5fcab816dc5c861041de75"
    },
    {
      "path": "B0x_Staking_Rich_List_logs_testnet.json",
      "size": 819,
      "modified": "2025-10-27T20:25:53.558750Z",
      "md5": "dcffe8134870942f39b10c1bd7252839"
    },
    {
      "path": "RichList__MainnetETH_holders.json",
      "size": 1076,
      "modified": "2025-10-27T20:25:53.829749Z",
      "md5": "0257f1b9452983ae2d234b70aff3d276"
    },
    {
      "path": "githubERC20RewardsTestnet.json",
      "size": 182,
      "modified": "2025-10-27T20:25:42.981764Z",
      "md5": "f4559b4fa75caf8238c951742f6506a2"
    },
    {
      "path": "uu_mined_blocks_testnet.json",
      "size": 650878,
      "modified": "2025-10-27T20:25:54.406749Z",
      "md5": "90ab2878b47bcda10ce73aa97f010f88"
    }
  ]
}