{
  "last_updated": "2025-12-04T06:40:47.301292Z",
  "source_url": "https://data.bzerox.org/graph/",
  "stats": {
    "downloaded": 0,
    "updated": 6,
    "errors": 0,
    "skipped": 3
  },
  "files": [
    {
      "path": "RichList_RightsTo0xBTC_MainnetETH_holders.json",
      "size": 770,
      "modified": "2025-12-04T06:40:47.071190Z",
      "md5": "e317358d973dcaf1a34b56d1fb4eb2e5"
    },
    {
      "path": "mined_blocks_testnet.json",
      "size": 278126,
      "modified": "2025-12-04T06:40:41.820218Z",
      "md5": "ec38b30e891cf22ec21ad931cfd3bb82"
    },
    {
      "path": "testnet_uniswap_v4_data.json",
      "size": 14349,
      "modified": "2025-12-04T06:40:47.170189Z",
      "md5": "9c14b74f1e9bed3ce4c9fb3574466207"
    },
    {
      "path": "price_data_bwork.json",
      "size": 6926,
      "modified": "2025-12-04T06:40:47.143189Z",
      "md5": "d7d455f6c1e0e37f2786d0c6a04a647e"
    },
    {
      "path": "mined_blocks_testnet.js",
      "size": 354,
      "modified": "2025-12-04T06:40:41.819218Z",
      "md5": "04f660f0973f48b1fa99b58e20d0b82d"
    },
    {
      "path": "RichList_B0x_testnet.json",
      "size": 1774,
      "modified": "2025-12-04T06:40:41.818218Z",
      "md5": "fa8d673c18b245cfbb3bb8d7ee22c304"
    },
    {
      "path": "RichList_B0x_testnet_miners.json",
      "size": 780,
      "modified": "2025-12-04T06:40:41.818218Z",
      "md5": "7e4c23b12fc32d2b3624536115e28303"
    },
    {
      "path": "B0x_Staking_Rich_List_logs_testnet.json",
      "size": 819,
      "modified": "2025-12-04T06:40:47.007190Z",
      "md5": "162703283c618a88d3d8649ef0f20712"
    },
    {
      "path": "RichList__MainnetETH_holders.json",
      "size": 1074,
      "modified": "2025-12-04T06:40:47.093190Z",
      "md5": "70c43dd8d55bc26e17908113e278fcb7"
    },
    {
      "path": "githubERC20RewardsTestnet.json",
      "size": 182,
      "modified": "2025-12-04T06:40:41.818218Z",
      "md5": "f4559b4fa75caf8238c951742f6506a2"
    },
    {
      "path": "uu_mined_blocks_testnet.json",
      "size": 691202,
      "modified": "2025-12-04T06:40:47.300189Z",
      "md5": "4458d26f0d02d828f645f3f11aadc030"
    }
  ]
}