{
  "last_updated": "2025-10-19T07:42:31.318184Z",
  "source_url": "https://data.bzerox.org/graph/",
  "stats": {
    "downloaded": 0,
    "updated": 8,
    "errors": 0,
    "skipped": 1
  },
  "files": [
    {
      "path": "uu_mined_blocks_testnet.json",
      "size": 474690,
      "modified": "2025-10-19T07:42:31.317681Z",
      "md5": "f24b668eba72e11cbe1d7cfcd9605338"
    },
    {
      "path": "RichList_B0x_testnet_miners.json",
      "size": 778,
      "modified": "2025-10-19T07:42:30.600388Z",
      "md5": "0e5b1d7ed751cce86cd60ce2ada12202"
    },
    {
      "path": "mined_blocks_testnet.json",
      "size": 278126,
      "modified": "2025-10-19T07:42:23.410459Z",
      "md5": "ec38b30e891cf22ec21ad931cfd3bb82"
    },
    {
      "path": "githubERC20RewardsTestnet.json",
      "size": 182,
      "modified": "2025-10-19T07:42:23.409374Z",
      "md5": "f4559b4fa75caf8238c951742f6506a2"
    },
    {
      "path": "RichList_B0x_testnet.json",
      "size": 1771,
      "modified": "2025-10-19T07:42:30.528275Z",
      "md5": "720b82d6fe8467c5743e820d4d49ed4c"
    },
    {
      "path": "RichList__MainnetETH_holders.json",
      "size": 1076,
      "modified": "2025-10-19T07:42:30.734506Z",
      "md5": "69b52e70ecae5c56a3577eb5202557d6"
    },
    {
      "path": "B0x_Staking_Rich_List_logs_testnet.json",
      "size": 819,
      "modified": "2025-10-19T07:42:30.456079Z",
      "md5": "a2566599ea69c11355d650c2a22abe70"
    },
    {
      "path": "RichList_RightsTo0xBTC_MainnetETH_holders.json",
      "size": 770,
      "modified": "2025-10-19T07:42:30.667680Z",
      "md5": "86c221bfff99d2e6e81735f1bd830ad9"
    },
    {
      "path": "mined_blocks_testnet.js",
      "size": 354,
      "modified": "2025-10-19T07:42:23.409459Z",
      "md5": "04f660f0973f48b1fa99b58e20d0b82d"
    },
    {
      "path": "price_data_bwork.json",
      "size": 6868,
      "modified": "2025-10-19T07:42:30.889309Z",
      "md5": "f35abb332091fa9099c886f58dca2207"
    },
    {
      "path": "testnet_uniswap_v4_data.json",
      "size": 14349,
      "modified": "2025-10-19T07:42:30.963971Z",
      "md5": "9c2808ebd2a348538a4143f863dc4a5c"
    }
  ]
}