{
  "last_updated": "2025-11-20T17:19:50.464858Z",
  "source_url": "https://data.bzerox.org/graph/",
  "stats": {
    "downloaded": 0,
    "updated": 6,
    "errors": 0,
    "skipped": 3
  },
  "files": [
    {
      "path": "RichList_RightsTo0xBTC_MainnetETH_holders.json",
      "size": 770,
      "modified": "2025-11-20T17:19:49.995440Z",
      "md5": "eb6dd673c6f26ae9184dcf4a3eeb41cd"
    },
    {
      "path": "mined_blocks_testnet.json",
      "size": 278126,
      "modified": "2025-11-20T17:19:43.950409Z",
      "md5": "ec38b30e891cf22ec21ad931cfd3bb82"
    },
    {
      "path": "testnet_uniswap_v4_data.json",
      "size": 14349,
      "modified": "2025-11-20T17:19:50.184440Z",
      "md5": "f928d10010d4dabb0dfddb95325575fd"
    },
    {
      "path": "price_data_bwork.json",
      "size": 6953,
      "modified": "2025-11-20T17:19:50.133440Z",
      "md5": "b10619a8b8e029f190a2c0d7cfe34ba7"
    },
    {
      "path": "mined_blocks_testnet.js",
      "size": 354,
      "modified": "2025-11-20T17:19:43.949409Z",
      "md5": "04f660f0973f48b1fa99b58e20d0b82d"
    },
    {
      "path": "RichList_B0x_testnet.json",
      "size": 1774,
      "modified": "2025-11-20T17:19:43.949409Z",
      "md5": "fa8d673c18b245cfbb3bb8d7ee22c304"
    },
    {
      "path": "RichList_B0x_testnet_miners.json",
      "size": 780,
      "modified": "2025-11-20T17:19:43.949409Z",
      "md5": "7e4c23b12fc32d2b3624536115e28303"
    },
    {
      "path": "B0x_Staking_Rich_List_logs_testnet.json",
      "size": 819,
      "modified": "2025-11-20T17:19:49.862439Z",
      "md5": "b04d47323a65772db81a57e5cd1ddb2d"
    },
    {
      "path": "RichList__MainnetETH_holders.json",
      "size": 1074,
      "modified": "2025-11-20T17:19:50.041440Z",
      "md5": "86fced3d72b2d73b26602524a0278f9b"
    },
    {
      "path": "githubERC20RewardsTestnet.json",
      "size": 182,
      "modified": "2025-11-20T17:19:43.949409Z",
      "md5": "f4559b4fa75caf8238c951742f6506a2"
    },
    {
      "path": "uu_mined_blocks_testnet.json",
      "size": 682322,
      "modified": "2025-11-20T17:19:50.463417Z",
      "md5": "7bc6d20b48bfce0f2b6f4542edf7d39c"
    }
  ]
}