{
  "last_updated": "2025-12-17T00:43:16.793303Z",
  "source_url": "https://data.bzerox.org/graph/",
  "stats": {
    "downloaded": 0,
    "updated": 6,
    "errors": 0,
    "skipped": 3
  },
  "files": [
    {
      "path": "RichList_RightsTo0xBTC_MainnetETH_holders.json",
      "size": 770,
      "modified": "2025-12-17T00:43:16.568460Z",
      "md5": "f597633032757999208607e87f9c95ba"
    },
    {
      "path": "mined_blocks_testnet.json",
      "size": 278126,
      "modified": "2025-12-17T00:43:11.476419Z",
      "md5": "ec38b30e891cf22ec21ad931cfd3bb82"
    },
    {
      "path": "testnet_uniswap_v4_data.json",
      "size": 14349,
      "modified": "2025-12-17T00:43:16.657460Z",
      "md5": "04cf383494004552526f128cceb70985"
    },
    {
      "path": "price_data_bwork.json",
      "size": 6870,
      "modified": "2025-12-17T00:43:16.630460Z",
      "md5": "28ca909205211661b9478aa3b82c840a"
    },
    {
      "path": "mined_blocks_testnet.js",
      "size": 354,
      "modified": "2025-12-17T00:43:11.475420Z",
      "md5": "04f660f0973f48b1fa99b58e20d0b82d"
    },
    {
      "path": "RichList_B0x_testnet.json",
      "size": 1774,
      "modified": "2025-12-17T00:43:11.475420Z",
      "md5": "fa8d673c18b245cfbb3bb8d7ee22c304"
    },
    {
      "path": "RichList_B0x_testnet_miners.json",
      "size": 780,
      "modified": "2025-12-17T00:43:11.475420Z",
      "md5": "7e4c23b12fc32d2b3624536115e28303"
    },
    {
      "path": "B0x_Staking_Rich_List_logs_testnet.json",
      "size": 819,
      "modified": "2025-12-17T00:43:16.503459Z",
      "md5": "d9485797b45075cfba3d9872cd6f291c"
    },
    {
      "path": "RichList__MainnetETH_holders.json",
      "size": 1074,
      "modified": "2025-12-17T00:43:16.588460Z",
      "md5": "7b7dc179a34dd364c6cde89cda08825b"
    },
    {
      "path": "githubERC20RewardsTestnet.json",
      "size": 182,
      "modified": "2025-12-17T00:43:11.475420Z",
      "md5": "f4559b4fa75caf8238c951742f6506a2"
    },
    {
      "path": "uu_mined_blocks_testnet.json",
      "size": 691202,
      "modified": "2025-12-17T00:43:16.791460Z",
      "md5": "0f99cbea59ebeb8a9d7aae72b314613f"
    }
  ]
}