{
  "last_updated": "2026-03-23T16:42:07.209230Z",
  "source_url": "https://data.bzerox.org/graph/",
  "stats": {
    "downloaded": 0,
    "updated": 8,
    "errors": 0,
    "skipped": 1
  },
  "files": [
    {
      "path": "githubERC20RewardsTestnet.json",
      "size": 182,
      "modified": "2026-03-23T16:41:54.205043Z",
      "md5": "f4559b4fa75caf8238c951742f6506a2"
    },
    {
      "path": "B0x_Staking_Rich_List_logs_testnet.json",
      "size": 819,
      "modified": "2026-03-23T16:42:06.671293Z",
      "md5": "4af3765dae501d9b3e825c132550f350"
    },
    {
      "path": "mined_blocks_testnet.js",
      "size": 354,
      "modified": "2026-03-23T16:41:54.205043Z",
      "md5": "04f660f0973f48b1fa99b58e20d0b82d"
    },
    {
      "path": "RichList__MainnetETH_holders.json",
      "size": 1074,
      "modified": "2026-03-23T16:42:06.814109Z",
      "md5": "12d250c478b407fa5135b9a98b4c595b"
    },
    {
      "path": "price_data_bwork.json",
      "size": 7024,
      "modified": "2026-03-23T16:42:06.890637Z",
      "md5": "997ddeea66dee1021f16426daf9ee967"
    },
    {
      "path": "RichList_RightsTo0xBTC_MainnetETH_holders.json",
      "size": 770,
      "modified": "2026-03-23T16:42:06.781014Z",
      "md5": "a0e08a11a2a387b512ba80da5e34933c"
    },
    {
      "path": "uu_mined_blocks_testnet.json",
      "size": 691202,
      "modified": "2026-03-23T16:42:07.208565Z",
      "md5": "c758c70bcff424c8b12aaea8e15c17a2"
    },
    {
      "path": "testnet_uniswap_v4_data.json",
      "size": 14349,
      "modified": "2026-03-23T16:42:06.927638Z",
      "md5": "debff98d9a3d5796607b03c6a459ef96"
    },
    {
      "path": "mined_blocks_testnet.json",
      "size": 278126,
      "modified": "2026-03-23T16:41:54.205043Z",
      "md5": "ec38b30e891cf22ec21ad931cfd3bb82"
    },
    {
      "path": "RichList_B0x_testnet.json",
      "size": 2238,
      "modified": "2026-03-23T16:42:06.711701Z",
      "md5": "22b4bcde5f7073c35185316415a7358d"
    },
    {
      "path": "RichList_B0x_testnet_miners.json",
      "size": 1106,
      "modified": "2026-03-23T16:42:06.746302Z",
      "md5": "ac63e8d54e134189455e142f917f2247"
    }
  ]
}