{
  "last_updated": "2025-12-20T04:43:47.375078Z",
  "source_url": "https://data.bzerox.org/graph/",
  "stats": {
    "downloaded": 0,
    "updated": 6,
    "errors": 0,
    "skipped": 3
  },
  "files": [
    {
      "path": "RichList_RightsTo0xBTC_MainnetETH_holders.json",
      "size": 770,
      "modified": "2025-12-20T04:43:46.749420Z",
      "md5": "6ce29ea1897769171c837663fab701ad"
    },
    {
      "path": "mined_blocks_testnet.json",
      "size": 278126,
      "modified": "2025-12-20T04:43:41.926443Z",
      "md5": "ec38b30e891cf22ec21ad931cfd3bb82"
    },
    {
      "path": "testnet_uniswap_v4_data.json",
      "size": 14349,
      "modified": "2025-12-20T04:43:47.024418Z",
      "md5": "5d083293a8880f5df9379ca27f25e760"
    },
    {
      "path": "price_data_bwork.json",
      "size": 6872,
      "modified": "2025-12-20T04:43:46.955419Z",
      "md5": "2cbe37bbf99bd0b3a12eb5411dde7d96"
    },
    {
      "path": "mined_blocks_testnet.js",
      "size": 354,
      "modified": "2025-12-20T04:43:41.925442Z",
      "md5": "04f660f0973f48b1fa99b58e20d0b82d"
    },
    {
      "path": "RichList_B0x_testnet.json",
      "size": 1774,
      "modified": "2025-12-20T04:43:41.924443Z",
      "md5": "fa8d673c18b245cfbb3bb8d7ee22c304"
    },
    {
      "path": "RichList_B0x_testnet_miners.json",
      "size": 780,
      "modified": "2025-12-20T04:43:41.924443Z",
      "md5": "7e4c23b12fc32d2b3624536115e28303"
    },
    {
      "path": "B0x_Staking_Rich_List_logs_testnet.json",
      "size": 819,
      "modified": "2025-12-20T04:43:46.543421Z",
      "md5": "c6f7bc0cc1961479dfae6c33b18ff8d2"
    },
    {
      "path": "RichList__MainnetETH_holders.json",
      "size": 1074,
      "modified": "2025-12-20T04:43:46.820419Z",
      "md5": "1464a560d9b1359f43e33d3475df8c10"
    },
    {
      "path": "githubERC20RewardsTestnet.json",
      "size": 182,
      "modified": "2025-12-20T04:43:41.925442Z",
      "md5": "f4559b4fa75caf8238c951742f6506a2"
    },
    {
      "path": "uu_mined_blocks_testnet.json",
      "size": 691202,
      "modified": "2025-12-20T04:43:47.373418Z",
      "md5": "91e9b396a3b2034e23cd923ebb38882c"
    }
  ]
}