{
  "last_updated": "2026-03-08T12:44:20.519794Z",
  "source_url": "https://data.bzerox.org/graph/",
  "stats": {
    "downloaded": 0,
    "updated": 8,
    "errors": 0,
    "skipped": 1
  },
  "files": [
    {
      "path": "githubERC20RewardsTestnet.json",
      "size": 182,
      "modified": "2026-03-08T12:44:07.458728Z",
      "md5": "f4559b4fa75caf8238c951742f6506a2"
    },
    {
      "path": "B0x_Staking_Rich_List_logs_testnet.json",
      "size": 819,
      "modified": "2026-03-08T12:44:19.975275Z",
      "md5": "c47a9beb2a2e8a9ba63b0b894e5bb66c"
    },
    {
      "path": "mined_blocks_testnet.js",
      "size": 354,
      "modified": "2026-03-08T12:44:07.458728Z",
      "md5": "04f660f0973f48b1fa99b58e20d0b82d"
    },
    {
      "path": "RichList__MainnetETH_holders.json",
      "size": 1074,
      "modified": "2026-03-08T12:44:20.142021Z",
      "md5": "f979afca80dc9c86e8c0d99e53bd4bad"
    },
    {
      "path": "price_data_bwork.json",
      "size": 7025,
      "modified": "2026-03-08T12:44:20.237862Z",
      "md5": "dc33ad44dee0e3a39cc183abc3a83b6c"
    },
    {
      "path": "RichList_RightsTo0xBTC_MainnetETH_holders.json",
      "size": 770,
      "modified": "2026-03-08T12:44:20.098913Z",
      "md5": "b7f0a7e37ec3f139ccf73bba0fc912e5"
    },
    {
      "path": "uu_mined_blocks_testnet.json",
      "size": 691202,
      "modified": "2026-03-08T12:44:20.518822Z",
      "md5": "d25614741b99e581270442de017e1c1a"
    },
    {
      "path": "testnet_uniswap_v4_data.json",
      "size": 14349,
      "modified": "2026-03-08T12:44:20.284906Z",
      "md5": "a2744e6d7a19becfc6827daedbd3466c"
    },
    {
      "path": "mined_blocks_testnet.json",
      "size": 278126,
      "modified": "2026-03-08T12:44:07.459049Z",
      "md5": "ec38b30e891cf22ec21ad931cfd3bb82"
    },
    {
      "path": "RichList_B0x_testnet.json",
      "size": 2238,
      "modified": "2026-03-08T12:44:20.018644Z",
      "md5": "a1ba51836f8f1422a06e04ad364ba8a2"
    },
    {
      "path": "RichList_B0x_testnet_miners.json",
      "size": 1106,
      "modified": "2026-03-08T12:44:20.059197Z",
      "md5": "08534fbc9b22707e0864bad5df21a689"
    }
  ]
}