{
  "last_updated": "2025-11-30T11:24:13.181651Z",
  "source_url": "https://data.bzerox.org/graph/",
  "stats": {
    "downloaded": 0,
    "updated": 6,
    "errors": 0,
    "skipped": 3
  },
  "files": [
    {
      "path": "RichList_RightsTo0xBTC_MainnetETH_holders.json",
      "size": 770,
      "modified": "2025-11-30T11:24:12.743912Z",
      "md5": "2059b82129200c93e84fbf21652f6939"
    },
    {
      "path": "mined_blocks_testnet.json",
      "size": 278126,
      "modified": "2025-11-30T11:24:07.270885Z",
      "md5": "ec38b30e891cf22ec21ad931cfd3bb82"
    },
    {
      "path": "testnet_uniswap_v4_data.json",
      "size": 14349,
      "modified": "2025-11-30T11:24:12.927913Z",
      "md5": "09c352a9966ae70a5d1eb0b98677565a"
    },
    {
      "path": "price_data_bwork.json",
      "size": 6922,
      "modified": "2025-11-30T11:24:12.879913Z",
      "md5": "d3834de893d6ef2cb0d634eb0ed3e381"
    },
    {
      "path": "mined_blocks_testnet.js",
      "size": 354,
      "modified": "2025-11-30T11:24:07.269885Z",
      "md5": "04f660f0973f48b1fa99b58e20d0b82d"
    },
    {
      "path": "RichList_B0x_testnet.json",
      "size": 1774,
      "modified": "2025-11-30T11:24:07.269885Z",
      "md5": "fa8d673c18b245cfbb3bb8d7ee22c304"
    },
    {
      "path": "RichList_B0x_testnet_miners.json",
      "size": 780,
      "modified": "2025-11-30T11:24:07.269885Z",
      "md5": "7e4c23b12fc32d2b3624536115e28303"
    },
    {
      "path": "B0x_Staking_Rich_List_logs_testnet.json",
      "size": 819,
      "modified": "2025-11-30T11:24:12.610912Z",
      "md5": "4a646d70da6c870415f3bf2b96b723aa"
    },
    {
      "path": "RichList__MainnetETH_holders.json",
      "size": 1074,
      "modified": "2025-11-30T11:24:12.786912Z",
      "md5": "4bcb4b06c5f2fec2c69a6e0c4bab8a63"
    },
    {
      "path": "githubERC20RewardsTestnet.json",
      "size": 182,
      "modified": "2025-11-30T11:24:07.269885Z",
      "md5": "f4559b4fa75caf8238c951742f6506a2"
    },
    {
      "path": "uu_mined_blocks_testnet.json",
      "size": 691202,
      "modified": "2025-11-30T11:24:13.179914Z",
      "md5": "3bd4350fe313fb5e6b3774778eaf6644"
    }
  ]
}