{
  "last_updated": "2026-02-10T11:30:11.884722Z",
  "source_url": "https://data.bzerox.org/graph/",
  "stats": {
    "downloaded": 0,
    "updated": 8,
    "errors": 0,
    "skipped": 1
  },
  "files": [
    {
      "path": "RichList_RightsTo0xBTC_MainnetETH_holders.json",
      "size": 770,
      "modified": "2026-02-10T11:30:11.452092Z",
      "md5": "e1948b7a93ad630fb4018b210476218d"
    },
    {
      "path": "mined_blocks_testnet.json",
      "size": 278126,
      "modified": "2026-02-10T11:30:00.528159Z",
      "md5": "ec38b30e891cf22ec21ad931cfd3bb82"
    },
    {
      "path": "testnet_uniswap_v4_data.json",
      "size": 14349,
      "modified": "2026-02-10T11:30:11.633091Z",
      "md5": "74f5ab240d92eb8273d56a3c25be29e1"
    },
    {
      "path": "price_data_bwork.json",
      "size": 6936,
      "modified": "2026-02-10T11:30:11.586092Z",
      "md5": "54c4eec497f32001d298d168fc6a7c41"
    },
    {
      "path": "mined_blocks_testnet.js",
      "size": 354,
      "modified": "2026-02-10T11:30:00.527159Z",
      "md5": "04f660f0973f48b1fa99b58e20d0b82d"
    },
    {
      "path": "RichList_B0x_testnet.json",
      "size": 2238,
      "modified": "2026-02-10T11:30:11.369093Z",
      "md5": "5d9fd4253168972b9c0bbacc88080cc2"
    },
    {
      "path": "RichList_B0x_testnet_miners.json",
      "size": 1106,
      "modified": "2026-02-10T11:30:11.411093Z",
      "md5": "7a4308b42c2e670d72aec0bfa684232e"
    },
    {
      "path": "B0x_Staking_Rich_List_logs_testnet.json",
      "size": 819,
      "modified": "2026-02-10T11:30:11.322093Z",
      "md5": "1f217f3b531c7dd433fd883f5be1efd2"
    },
    {
      "path": "RichList__MainnetETH_holders.json",
      "size": 1074,
      "modified": "2026-02-10T11:30:11.493092Z",
      "md5": "ce318b9eb7d4e70b4ea99c8b16ea4a6b"
    },
    {
      "path": "githubERC20RewardsTestnet.json",
      "size": 182,
      "modified": "2026-02-10T11:30:00.527159Z",
      "md5": "f4559b4fa75caf8238c951742f6506a2"
    },
    {
      "path": "uu_mined_blocks_testnet.json",
      "size": 691202,
      "modified": "2026-02-10T11:30:11.883090Z",
      "md5": "a2644f29181d796f0d86696544435d71"
    }
  ]
}