{
  "last_updated": "2025-12-31T17:00:00.429421Z",
  "source_url": "https://data.bzerox.org/graph/",
  "stats": {
    "downloaded": 0,
    "updated": 5,
    "errors": 0,
    "skipped": 4
  },
  "files": [
    {
      "path": "RichList_RightsTo0xBTC_MainnetETH_holders.json",
      "size": 770,
      "modified": "2025-12-31T16:59:59.220874Z",
      "md5": "4200a280279b213be26ce8f2ed46112c"
    },
    {
      "path": "mined_blocks_testnet.json",
      "size": 278126,
      "modified": "2025-12-31T16:59:55.104890Z",
      "md5": "ec38b30e891cf22ec21ad931cfd3bb82"
    },
    {
      "path": "testnet_uniswap_v4_data.json",
      "size": 14349,
      "modified": "2025-12-31T16:59:59.380874Z",
      "md5": "ef4c90c0757bf507a402254bbe408a55"
    },
    {
      "path": "price_data_bwork.json",
      "size": 6979,
      "modified": "2025-12-31T16:59:59.338874Z",
      "md5": "a5970517e09616dbe6a7788ab9ec390f"
    },
    {
      "path": "mined_blocks_testnet.js",
      "size": 354,
      "modified": "2025-12-31T16:59:55.103890Z",
      "md5": "04f660f0973f48b1fa99b58e20d0b82d"
    },
    {
      "path": "RichList_B0x_testnet.json",
      "size": 1774,
      "modified": "2025-12-31T16:59:55.103890Z",
      "md5": "fa8d673c18b245cfbb3bb8d7ee22c304"
    },
    {
      "path": "RichList_B0x_testnet_miners.json",
      "size": 780,
      "modified": "2025-12-31T16:59:55.103890Z",
      "md5": "7e4c23b12fc32d2b3624536115e28303"
    },
    {
      "path": "B0x_Staking_Rich_List_logs_testnet.json",
      "size": 819,
      "modified": "2025-12-31T16:59:55.103890Z",
      "md5": "82af9a64ec7fde2fed2fc8e0ebad1e4b"
    },
    {
      "path": "RichList__MainnetETH_holders.json",
      "size": 1074,
      "modified": "2025-12-31T16:59:59.258874Z",
      "md5": "5f4c5aedb048b5039b673873318c0bba"
    },
    {
      "path": "githubERC20RewardsTestnet.json",
      "size": 182,
      "modified": "2025-12-31T16:59:55.103890Z",
      "md5": "f4559b4fa75caf8238c951742f6506a2"
    },
    {
      "path": "uu_mined_blocks_testnet.json",
      "size": 691202,
      "modified": "2025-12-31T17:00:00.426870Z",
      "md5": "9771d522082b06ef42bc22443f9d4548"
    }
  ]
}