{
  "last_updated": "2026-02-23T15:28:04.175931Z",
  "source_url": "https://data.bzerox.org/graph/",
  "stats": {
    "downloaded": 0,
    "updated": 8,
    "errors": 0,
    "skipped": 1
  },
  "files": [
    {
      "path": "RichList_RightsTo0xBTC_MainnetETH_holders.json",
      "size": 770,
      "modified": "2026-02-23T15:28:03.549143Z",
      "md5": "97ad456d6d4445d06d28211b969bb2c0"
    },
    {
      "path": "mined_blocks_testnet.json",
      "size": 278126,
      "modified": "2026-02-23T15:27:52.370166Z",
      "md5": "ec38b30e891cf22ec21ad931cfd3bb82"
    },
    {
      "path": "testnet_uniswap_v4_data.json",
      "size": 14349,
      "modified": "2026-02-23T15:28:03.814143Z",
      "md5": "9c9d6f48537285043b489e1ecfc4c88b"
    },
    {
      "path": "price_data_bwork.json",
      "size": 7011,
      "modified": "2026-02-23T15:28:03.746143Z",
      "md5": "83fd86d55a864225cf5b2cc50e2e8b75"
    },
    {
      "path": "mined_blocks_testnet.js",
      "size": 354,
      "modified": "2026-02-23T15:27:52.369166Z",
      "md5": "04f660f0973f48b1fa99b58e20d0b82d"
    },
    {
      "path": "RichList_B0x_testnet.json",
      "size": 2238,
      "modified": "2026-02-23T15:28:03.354143Z",
      "md5": "dcd60486d9334a51e5ff006badd84b71"
    },
    {
      "path": "RichList_B0x_testnet_miners.json",
      "size": 1106,
      "modified": "2026-02-23T15:28:03.453143Z",
      "md5": "45795092dead32d0f3f137714f4b5a9c"
    },
    {
      "path": "B0x_Staking_Rich_List_logs_testnet.json",
      "size": 819,
      "modified": "2026-02-23T15:28:03.281143Z",
      "md5": "4340b41ec729cb40c84822531148e649"
    },
    {
      "path": "RichList__MainnetETH_holders.json",
      "size": 1074,
      "modified": "2026-02-23T15:28:03.615143Z",
      "md5": "90a68e32132e870328d120a28e75fca5"
    },
    {
      "path": "githubERC20RewardsTestnet.json",
      "size": 182,
      "modified": "2026-02-23T15:27:52.369166Z",
      "md5": "f4559b4fa75caf8238c951742f6506a2"
    },
    {
      "path": "uu_mined_blocks_testnet.json",
      "size": 691202,
      "modified": "2026-02-23T15:28:04.174143Z",
      "md5": "b19c9314bdd38e0b9528172a7442cf18"
    }
  ]
}