{
  "last_updated": "2025-10-02T13:33:12.753891Z",
  "source_url": "https://data.bzerox.org/graph/",
  "stats": {
    "downloaded": 0,
    "updated": 8,
    "errors": 0,
    "skipped": 1
  },
  "files": [
    {
      "path": "RichList_RightsTo0xBTC_MainnetETH_holders.json",
      "size": 770,
      "modified": "2025-10-02T13:33:12.557570Z",
      "md5": "24287eb24f5efb8d112361f5fc91e6f8"
    },
    {
      "path": "mined_blocks_testnet.json",
      "size": 278126,
      "modified": "2025-10-02T13:33:08.442554Z",
      "md5": "ec38b30e891cf22ec21ad931cfd3bb82"
    },
    {
      "path": "testnet_uniswap_v4_data.json",
      "size": 14349,
      "modified": "2025-10-02T13:33:12.640570Z",
      "md5": "da1b31d22473d2f890f7714b8494e781"
    },
    {
      "path": "price_data_bwork.json",
      "size": 6925,
      "modified": "2025-10-02T13:33:12.617570Z",
      "md5": "835d199289495365ef68e067801a59c6"
    },
    {
      "path": "mined_blocks_testnet.js",
      "size": 354,
      "modified": "2025-10-02T13:33:08.441554Z",
      "md5": "04f660f0973f48b1fa99b58e20d0b82d"
    },
    {
      "path": "RichList_B0x_testnet.json",
      "size": 1771,
      "modified": "2025-10-02T13:33:12.519569Z",
      "md5": "2c04ce5f22572e003ebe3a8e704bfa3d"
    },
    {
      "path": "RichList_B0x_testnet_miners.json",
      "size": 778,
      "modified": "2025-10-02T13:33:12.538569Z",
      "md5": "7d9969237e0f8ebda2fd9b4f7f622c3e"
    },
    {
      "path": "B0x_Staking_Rich_List_logs_testnet.json",
      "size": 819,
      "modified": "2025-10-02T13:33:12.493569Z",
      "md5": "d13d1e6baf9897a4ec221c33cf34fa06"
    },
    {
      "path": "RichList__MainnetETH_holders.json",
      "size": 1076,
      "modified": "2025-10-02T13:33:12.577570Z",
      "md5": "697636d71d43432adf0d8cb1f333063c"
    },
    {
      "path": "githubERC20RewardsTestnet.json",
      "size": 182,
      "modified": "2025-10-02T13:33:08.441554Z",
      "md5": "f4559b4fa75caf8238c951742f6506a2"
    },
    {
      "path": "uu_mined_blocks_testnet.json",
      "size": 474690,
      "modified": "2025-10-02T13:33:12.752570Z",
      "md5": "7a7897d257501972d819e758b55405ad"
    }
  ]
}