{
  "last_updated": "2025-10-19T13:39:17.148729Z",
  "source_url": "https://data.bzerox.org/graph/",
  "stats": {
    "downloaded": 0,
    "updated": 8,
    "errors": 0,
    "skipped": 1
  },
  "files": [
    {
      "path": "uu_mined_blocks_testnet.json",
      "size": 474690,
      "modified": "2025-10-19T13:39:17.148245Z",
      "md5": "efcdcfea50cfbe9518020066979d98d5"
    },
    {
      "path": "RichList_B0x_testnet_miners.json",
      "size": 778,
      "modified": "2025-10-19T13:39:16.500920Z",
      "md5": "0394e60da83519fd8c9ab61116391dd3"
    },
    {
      "path": "mined_blocks_testnet.json",
      "size": 278126,
      "modified": "2025-10-19T13:39:09.935697Z",
      "md5": "ec38b30e891cf22ec21ad931cfd3bb82"
    },
    {
      "path": "githubERC20RewardsTestnet.json",
      "size": 182,
      "modified": "2025-10-19T13:39:09.934855Z",
      "md5": "f4559b4fa75caf8238c951742f6506a2"
    },
    {
      "path": "RichList_B0x_testnet.json",
      "size": 1771,
      "modified": "2025-10-19T13:39:16.435974Z",
      "md5": "4ef10cc59280252b151ea1e60fa507f1"
    },
    {
      "path": "RichList__MainnetETH_holders.json",
      "size": 1076,
      "modified": "2025-10-19T13:39:16.635645Z",
      "md5": "e0c10fc27dea6daf3682266cb0b88f47"
    },
    {
      "path": "B0x_Staking_Rich_List_logs_testnet.json",
      "size": 819,
      "modified": "2025-10-19T13:39:16.363652Z",
      "md5": "5da6d02f462d2ca83bdaafcf3ec4c5fc"
    },
    {
      "path": "RichList_RightsTo0xBTC_MainnetETH_holders.json",
      "size": 770,
      "modified": "2025-10-19T13:39:16.567026Z",
      "md5": "6cae3ad63b1275dad308d366582debde"
    },
    {
      "path": "mined_blocks_testnet.js",
      "size": 354,
      "modified": "2025-10-19T13:39:09.934855Z",
      "md5": "04f660f0973f48b1fa99b58e20d0b82d"
    },
    {
      "path": "price_data_bwork.json",
      "size": 6925,
      "modified": "2025-10-19T13:39:16.777901Z",
      "md5": "d3af90cda0435118386cfc04a90eb50b"
    },
    {
      "path": "testnet_uniswap_v4_data.json",
      "size": 14349,
      "modified": "2025-10-19T13:39:16.848377Z",
      "md5": "e4281a3a97717066bf79c6ec391b7c7b"
    }
  ]
}