{
  "last_updated": "2026-03-14T19:56:12.522719Z",
  "source_url": "https://data.bzerox.org/graph/",
  "stats": {
    "downloaded": 0,
    "updated": 8,
    "errors": 0,
    "skipped": 1
  },
  "files": [
    {
      "path": "githubERC20RewardsTestnet.json",
      "size": 182,
      "modified": "2026-03-14T19:55:58.365145Z",
      "md5": "f4559b4fa75caf8238c951742f6506a2"
    },
    {
      "path": "B0x_Staking_Rich_List_logs_testnet.json",
      "size": 819,
      "modified": "2026-03-14T19:56:11.961002Z",
      "md5": "87a66b34cfa4ea0dae44aabd788904ae"
    },
    {
      "path": "mined_blocks_testnet.js",
      "size": 354,
      "modified": "2026-03-14T19:55:58.365145Z",
      "md5": "04f660f0973f48b1fa99b58e20d0b82d"
    },
    {
      "path": "RichList__MainnetETH_holders.json",
      "size": 1074,
      "modified": "2026-03-14T19:56:12.122644Z",
      "md5": "dee5375339e7f69e41ad628edd63c117"
    },
    {
      "path": "price_data_bwork.json",
      "size": 7081,
      "modified": "2026-03-14T19:56:12.200531Z",
      "md5": "7b7a0d497aecd59b60e5c853ee4518be"
    },
    {
      "path": "RichList_RightsTo0xBTC_MainnetETH_holders.json",
      "size": 770,
      "modified": "2026-03-14T19:56:12.083947Z",
      "md5": "7cb5553c73fe66f6d5afe76ac31745e0"
    },
    {
      "path": "uu_mined_blocks_testnet.json",
      "size": 691202,
      "modified": "2026-03-14T19:56:12.522030Z",
      "md5": "6700a508ba38bd02eb659c70c9eb11c3"
    },
    {
      "path": "testnet_uniswap_v4_data.json",
      "size": 14349,
      "modified": "2026-03-14T19:56:12.240758Z",
      "md5": "2b6ae5910289bb9aa89e98e23c292b3f"
    },
    {
      "path": "mined_blocks_testnet.json",
      "size": 278126,
      "modified": "2026-03-14T19:55:58.366145Z",
      "md5": "ec38b30e891cf22ec21ad931cfd3bb82"
    },
    {
      "path": "RichList_B0x_testnet.json",
      "size": 2238,
      "modified": "2026-03-14T19:56:12.006851Z",
      "md5": "670c748e52c74a6e8515fcfe2628d81b"
    },
    {
      "path": "RichList_B0x_testnet_miners.json",
      "size": 1106,
      "modified": "2026-03-14T19:56:12.046231Z",
      "md5": "dd932ad0d8190733fe6a63b8d2f8e28b"
    }
  ]
}